secretflowapis/__init__.py
secretflowapis/v1/__init__.py
secretflowapis/v1/common_pb2.py
secretflowapis/v1/common_pb2.pyi
secretflowapis/v1/common_pb2_grpc.py
secretflowapis/v1/status_pb2.py
secretflowapis/v1/status_pb2.pyi
secretflowapis/v1/status_pb2_grpc.py
secretflowapis/v1/sdc/__init__.py
secretflowapis/v1/sdc/core_pb2.py
secretflowapis/v1/sdc/core_pb2.pyi
secretflowapis/v1/sdc/core_pb2_grpc.py
secretflowapis/v1/sdc/digital_envelope_pb2.py
secretflowapis/v1/sdc/digital_envelope_pb2.pyi
secretflowapis/v1/sdc/digital_envelope_pb2_grpc.py
secretflowapis/v1/sdc/authmanager/__init__.py
secretflowapis/v1/sdc/authmanager/auth_manager_pb2.py
secretflowapis/v1/sdc/authmanager/auth_manager_pb2.pyi
secretflowapis/v1/sdc/authmanager/auth_manager_pb2_grpc.py
secretflowapis/v1/sdc/dataagent/__init__.py
secretflowapis/v1/sdc/dataagent/data_agent_pb2.py
secretflowapis/v1/sdc/dataagent/data_agent_pb2.pyi
secretflowapis/v1/sdc/dataagent/data_agent_pb2_grpc.py
secretflowapis/v1/sdc/teeapps/__init__.py
secretflowapis/v1/sdc/teeapps/tee_task_params_pb2.py
secretflowapis/v1/sdc/teeapps/tee_task_params_pb2.pyi
secretflowapis/v1/sdc/teeapps/tee_task_params_pb2_grpc.py
secretflowapis/v2/__init__.py
secretflowapis/v2/common_pb2.py
secretflowapis/v2/common_pb2.pyi
secretflowapis/v2/common_pb2_grpc.py
secretflowapis/v2/status_pb2.py
secretflowapis/v2/status_pb2.pyi
secretflowapis/v2/status_pb2_grpc.py
secretflowapis/v2/sdc/__init__.py
secretflowapis/v2/sdc/jwt_pb2.py
secretflowapis/v2/sdc/jwt_pb2.pyi
secretflowapis/v2/sdc/jwt_pb2_grpc.py
secretflowapis/v2/sdc/ual_pb2.py
secretflowapis/v2/sdc/ual_pb2.pyi
secretflowapis/v2/sdc/ual_pb2_grpc.py
secretflowapis/v2/sdc/capsule_manager/__init__.py
secretflowapis/v2/sdc/capsule_manager/capsule_manager_pb2.py
secretflowapis/v2/sdc/capsule_manager/capsule_manager_pb2.pyi
secretflowapis/v2/sdc/capsule_manager/capsule_manager_pb2_grpc.py
secretflowapis/v2/sdc/data_capsule_proxy/__init__.py
sdc_apis-0.3.0.dev20250224.dist-info/METADATA
sdc_apis-0.3.0.dev20250224.dist-info/WHEEL
sdc_apis-0.3.0.dev20250224.dist-info/top_level.txt
sdc_apis-0.3.0.dev20250224.dist-info/RECORD
