Metadata-Version: 2.2
Name: sdc-apis
Version: 0.3.0.dev20250224
Summary: SecretFlow Data Capsule apis proto generated python
Home-page: https://github.com/secretflow/secure-data-capsule-apis
Author: secretflow
Author-email: secretflow-contact@service.alipay.com
License: Apache 2.0
Classifier: Programming Language :: Python :: 3
Classifier: License :: OSI Approved :: Apache Software License
Classifier: Operating System :: OS Independent
Requires-Dist: protobuf<5,>=4
Dynamic: author
Dynamic: author-email
Dynamic: classifier
Dynamic: description
Dynamic: description-content-type
Dynamic: home-page
Dynamic: license
Dynamic: requires-dist
Dynamic: summary
